dsets/__init__.py
dsets/dataset.py
dsets/downloader/__init__.py
dsets/downloader/mnist.py
dsets/interface.py
dsets/storage/__init__.py
dsets/storage/local.py
dsets-0.0.1.dist-info/WHEEL
dsets-0.0.1.dist-info/METADATA
dsets-0.0.1.dist-info/RECORD
