Metadata-Version: 2.1
Name: dsets
Version: 0.0.1
Summary: 
License: MIT
Author: Alexander Hungenberg
Author-email: alexander.hungenberg@gmail.com
Requires-Python: >=3.8,<4.0
Classifier: License :: OSI Approved :: MIT License
Classifier: Programming Language :: Python :: 3
Classifier: Programming Language :: Python :: 3.8
Classifier: Programming Language :: Python :: 3.9
Requires-Dist: numpy (>=1.19.1,<2.0.0)
